3_EXE/alu/HA.vhdl
library IEEE; 
use IEEE.std_logic_1164.all;

entity HA is
  port(A, B: in  std_logic;
       S, R: out std_logic); 
end HA;


architecture FLOW of HA is 
begin
    S <= A xor B; 
    R <= A and B; 
end FLOW;

TP4/FA.vhdl
-- lib
library ieee, work;
use ieee.std_logic_1164.all;
entity FA is
  port(A, B: in std_logic;
       cin: in std_logic;
       S: out std_logic;
       R: out std_logic
       );
end FA;


architecture flow of FA is
  signal S1, R1, R2: std_logic;
begin
  label0: entity work.HA(flow)
    port map (A, B, S1, R1);
  
  label1: entity work.HA(flow)
    port map (cin, S1, S, R2);

  R <= R1 or R2;
  
end flow;

3_EXE/adder4.vhdl
-- lib
library IEEE, work; 
--use ieee.math_real.all;
use ieee.numeric_std.all;
use ieee.std_logic_1164.all;
use work.FA;

entity adder4 is
  port ( A,B: in std_logic_vector( 3 downto 0 );
         cin: in std_logic;
         S : out std_logic_vector( 3 downto 0 );
         R : out std_logic );
end adder4;

architecture flow of adder4 is
  signal c: std_logic_vector(2 downto 0);

  Component FA is
    port (
    a, b, cin : in std_logic;
    s, cout : out std_logic);
  end Component;

begin


  inst_FA_1 : entity work.FA(flow) port map(a(0),b(0),cin,s(0),c(0));
  inst_FA_2 : entity work.FA(flow) port map(a(1),b(1),c(0),s(1),c(1));
  inst_FA_3 : entity work.FA(flow) port map(a(2),b(2),c(1),s(2),c(2));
  inst_FA_4 : entity work.FA(flow) port map(a(3),b(3),c(2),s(3),R);

end flow;

3_EXE/adder4_tb.vhdl
-- lib
library IEEE, work; 
use ieee.math_real.all;
use ieee.numeric_std.all;
use ieee.std_logic_1164.all;
use work.adder4;  
entity adder4_tb is
end adder4_tb;

architecture behav of adder4_tb is
  component adder4
  port (
    A,B: in std_logic_vector( 3 downto 0 );
    cin: in std_logic;
    S : out std_logic_vector( 3 downto 0 );
    R : out std_logic );
end component;

signal A, B, S : std_logic_vector(3 downto 0);
signal cin: std_logic;
signal R: std_logic;

begin

  adder4_inst : adder4
  port map (
    A => A,
    B => B,
    cin => cin,
    S => S,
    R => R
    );

  process

  variable seed1 :positive ;
  variable seed2 :positive ;
  variable re1 : integer;
  variable re2 : real ;
  
  variable din_rand : unsigned(3 downto 0);
  variable rand_A : unsigned(3 downto 0);
  variable rand_B : unsigned(3 downto 0);
  variable new_val : std_logic_vector(3 downto 0);

  begin

    A <= "0000";
    B <= "0011";
    cin <= '0';
    wait for 2 ns;
    assert (s = "0011") report "ERROR 0000+0011+0" severity FAILURE;
    assert (R = '0') report "ERROR 0000+0011 : r = 1" severity FAILURE;
    

    A <= "0000";
    B <= "0011";
    cin <= '1';
    wait for 2 ns;
    assert (s = "0100") report "ERROR 0000+0011+1" severity FAILURE;
    assert (R = '0') report "ERROR 0000+0011+1 : r = 1" severity FAILURE;

    for i in 0 to 100 loop
      -- generation aleatoire de valeurs pour din
      uniform (seed1,seed2,re2);
      re1 := integer (re2 * real(2**4 -1));
      rand_A := to_unsigned (re1,4);
      uniform (seed1,seed2,re2);
      re1 := integer (re2 * real(2**4 -1));
      rand_B := to_unsigned (re1,4);

      new_val := std_logic_vector(unsigned(rand_B) + unsigned(rand_A)+unsigned'( '0' & cin));
      A <= std_logic_vector(rand_A);
      B <= std_logic_vector(rand_B);
      cin <= cin;
      wait for 2 ns;
      assert (new_val = S) report "ERROR : " 
        &integer'image(to_integer(rand_A))&"+"
        &integer'image(to_integer(rand_B))&"+"
        &std_logic'image(cin)&"="
        &integer'image(to_integer(unsigned(S))) severity FAILURE;
    end loop;
    wait;
  end process;
  
end behav;

3_EXE/adder4.vcd
$date
  Wed Jan 23 20:15:48 2019
$end
$version
  GHDL v0
$end
$timescale
  1 fs
$end
$scope module standard $end
$upscope $end
$scope module math_real $end
$upscope $end
$scope module std_logic_1164 $end
$upscope $end
$scope module numeric_std $end
$upscope $end
$scope module adder4_tb $end
$var reg 4 ! a[3:0] $end
$var reg 4 " b[3:0] $end
$var reg 4 # s[3:0] $end
$var reg 1 $ cin $end
$var reg 1 % r $end
$scope module adder4_inst $end
$var reg 4 & a[3:0] $end
$var reg 4 ' b[3:0] $end
$var reg 1 ( cin $end
$var reg 4 ) s[3:0] $end
$var reg 1 * r $end
$var reg 3 + c[2:0] $end
$scope module inst_fa_1 $end
$var reg 1 , a $end
$var reg 1 - b $end
$var reg 1 . cin $end
$var reg 1 / s $end
$var reg 1 0 r $end
$var reg 1 1 s1 $end
$var reg 1 2 r1 $end
$var reg 1 3 r2 $end
$scope module label0 $end
$var reg 1 4 a $end
$var reg 1 5 b $end
$var reg 1 6 s $end
$var reg 1 7 r $end
$upscope $end
$scope module label1 $end
$var reg 1 8 a $end
$var reg 1 9 b $end
$var reg 1 : s $end
$var reg 1 ; r $end
$upscope $end
$upscope $end
$scope module inst_fa_2 $end
$var reg 1 < a $end
$var reg 1 = b $end
$var reg 1 > cin $end
$var reg 1 ? s $end
$var reg 1 @ r $end
$var reg 1 A s1 $end
$var reg 1 B r1 $end
$var reg 1 C r2 $end
$scope module label0 $end
$var reg 1 D a $end
$var reg 1 E b $end
$var reg 1 F s $end
$var reg 1 G r $end
$upscope $end
$scope module label1 $end
$var reg 1 H a $end
$var reg 1 I b $end
$var reg 1 J s $end
$var reg 1 K r $end
$upscope $end
$upscope $end
$scope module inst_fa_3 $end
$var reg 1 L a $end
$var reg 1 M b $end
$var reg 1 N cin $end
$var reg 1 O s $end
$var reg 1 P r $end
$var reg 1 Q s1 $end
$var reg 1 R r1 $end
$var reg 1 S r2 $end
$scope module label0 $end
$var reg 1 T a $end
$var reg 1 U b $end
$var reg 1 V s $end
$var reg 1 W r $end
$upscope $end
$scope module label1 $end
$var reg 1 X a $end
$var reg 1 Y b $end
$var reg 1 Z s $end
$var reg 1 [ r $end
$upscope $end
$upscope $end
$scope module inst_fa_4 $end
$var reg 1 \ a $end
$var reg 1 ] b $end
$var reg 1 ^ cin $end
$var reg 1 _ s $end
$var reg 1 ` r $end
$var reg 1 a s1 $end
$var reg 1 b r1 $end
$var reg 1 c r2 $end
$scope module label0 $end
$var reg 1 d a $end
$var reg 1 e b $end
$var reg 1 f s $end
$var reg 1 g r $end
$upscope $end
$scope module label1 $end
$var reg 1 h a $end
$var reg 1 i b $end
$var reg 1 j s $end
$var reg 1 k r $end
$upscope $end
$upscope $end
$upscope $end
$upscope $end
$enddefinitions $end
#0
b0000 !
b0011 "
b0011 #
0$
0%
b0000 &
b0011 '
0(
b0011 )
0*
b000 +
0,
1-
0.
1/
00
11
02
03
04
15
16
07
08
19
1:
0;
0<
1=
0>
1?
0@
1A
0B
0C
0D
1E
1F
0G
0H
1I
1J
0K
0L
0M
0N
0O
0P
0Q
0R
0S
0T
0U
0V
0W
0X
0Y
0Z
0[
0\
0]
0^
0_
0`
0a
0b
0c
0d
0e
0f
0g
0h
0i
0j
0k
#2000000
b0100 #
1$
1(
b0100 )
b011 +
1.
0/
10
13
18
0:
1;
1>
0?
1@
1C
1H
0J
1K
1N
1O
1X
1Z
#4000000
b1111 !
b1111 "
b1111 #
1%
b1111 &
b1111 '
b1111 )
1*
b111 +
1,
1/
01
12
03
14
06
17
09
1:
0;
1<
1?
0A
1B
0C
1D
0F
1G
0I
1J
0K
1L
1M
1P
1R
1T
1U
1W
1\
1]
1^
1_
1`
1b
1d
1e
1g
1h
1j
#6000000
b1010 !
b0101 "
b0000 #
1%
b1010 &
b0101 '
b0000 )
1*
b111 +
0,
0/
10
11
02
13
04
16
07
19
0:
1;
0=
1>
0?
1@
1A
0B
1C
0E
1F
0G
1H
1I
0J
1K
0L
1N
0O
1P
1Q
0R
1S
0T
1V
0W
1X
1Y
0Z
1[
0]
1^
0_
1`
1a
0b
1c
0e
1f
0g
1h
1i
0j
1k
#8000000
b0001 !
b0010 "
b0100 #
0%
b0001 &
b0010 '
b0100 )
0*
b011 +
1,
0-
14
05
0<
1=
0D
1E
0M
1O
0P
0Q
0S
0U
0V
0Y
1Z
0[
0\
0^
0_
0`
0a
0c
0d
0f
0h
0i
0j
0k
#10000000
b1010 !
b0001 "
b1100 #
b1010 &
b0001 '
b1100 )
0,
1-
04
15
1<
0=
1D
0E
1\
1_
1a
1d
1f
1i
1j
#12000000
b0011 !
b0011 "
b0111 #
b0011 &
b0011 '
b0111 )
1,
1/
01
12
03
14
06
17
09
1:
0;
1=
1?
0A
1B
0C
1E
0F
1G
0I
1J
0K
0\
0_
0a
0d
0f
0i
0j
#14000000
b1010 !
b0010 "
b1101 #
b1010 &
b0010 '
b1101 )
b010 +
0,
0-
00
02
04
05
07
0>
0?
0H
0J
1\
1_
1a
1d
1f
1i
1j
#16000000
b1110 !
b0001 #
1%
b1110 &
b0001 )
1*
b110 +
1L
0O
1P
1Q
1S
1T
1V
1Y
0Z
1[
1^
0_
1`
1c
1h
0j
1k
#18000000
b0100 !
b0100 "
b1001 #
0%
b0100 &
b0100 '
b1001 )
0*
b100 +
0<
0=
0@
0B
0D
0E
0G
1M
0N
0O
0Q
1R
0S
1U
0V
1W
0X
0Y
0Z
0[
0\
1_
0`
0a
0c
0d
0f
0i
1j
0k
#20000000
b1010 !
b1110 "
b1001 #
1%
b1010 &
b1110 '
b1001 )
1*
b110 +
1<
1=
1@
1B
1D
1E
1G
0L
1N
0O
1P
1Q
0R
1S
0T
1V
0W
1X
1Y
0Z
1[
1\
1]
1^
1_
1`
1b
1d
1e
1g
1h
1j
#22000000
b0001 !
b0000 #
1%
b0001 &
b0000 )
1*
b111 +
1,
0/
10
11
13
14
16
19
0:
1;
0<
1>
0?
1@
1A
0B
1C
0D
1F
0G
1H
1I
0J
1K
1N
0O
1P
1S
1X
0Z
1[
0\
1^
0_
1`
1a
0b
1c
0d
1f
0g
1h
1i
0j
1k
#24000000
b1110 !
b1101 #
b1110 &
b1101 )
b110 +
0,
1/
00
01
03
04
06
09
1:
0;
1<
0>
0?
0A
1B
0C
1D
0F
1G
0H
0I
0J
0K
1L
1O
0Q
1R
0S
1T
0V
1W
0Y
1Z
0[
1\
1_
0a
1b
0c
1d
0f
1g
0i
1j
0k
#26000000
b0111 !
b0001 "
b1001 #
0%
b0111 &
b0001 '
b1001 )
0*
b111 +
1,
1-
10
12
14
15
17
0=
1>
0?
1@
1A
0B
1C
0E
1F
0G
1H
1I
0J
1K
0M
1N
0O
1P
1Q
0R
1S
0U
1V
0W
1X
1Y
0Z
1[
0\
0]
1^
1_
0`
0b
0d
0e
0g
1h
1j
#28000000
b1110 !
b0000 #
1%
b1110 &
b0000 )
1*
b111 +
0,
0/
10
11
02
13
04
16
07
19
0:
1;
1>
0?
1@
1C
1H
0J
1K
1N
0O
1P
1S
1X
0Z
1[
1\
1^
0_
1`
1a
1c
1d
1f
1h
1i
0j
1k
#30000000
b0101 "
b0100 #
b0101 '
b0100 )
1M
1O
0Q
1R
0S
1U
0V
1W
0Y
1Z
0[
#32000000
b0010 !
b1101 "
b0000 #
1%
b0010 &
b1101 '
b0000 )
1*
b111 +
0L
0O
1P
1Q
0R
1S
0T
1V
0W
1Y
0Z
1[
0\
1]
1^
0_
1`
1c
0d
1e
1h
0j
1k
#34000000
b0000 !
b0011 "
b0100 #
0%
b0000 &
b0011 '
b0100 )
0*
b011 +
0<
1=
0D
1E
0M
1O
0P
0Q
0S
0U
0V
0Y
1Z
0[
0]
0^
0_
0`
0a
0c
0e
0f
0h
0i
0j
0k
#36000000
b1111 !
b1100 "
b1100 #
1%
b1111 &
b1100 '
b1100 )
1*
b111 +
1,
0-
14
05
1<
0=
1D
0E
1L
1M
1P
1R
1T
1U
1W
1\
1]
1^
1_
1`
1b
1d
1e
1g
1h
1j
#38000000
b0000 !
b0100 "
b0101 #
0%
b0000 &
b0100 '
b0101 )
0*
b000 +
0,
1/
00
01
03
04
06
09
1:
0;
0<
0>
0?
0@
0A
0C
0D
0F
0H
0I
0J
0K
0L
0N
1O
0P
1Q
0R
0S
0T
1V
0W
0X
1Y
1Z
0[
0\
0]
0^
0_
0`
0b
0d
0e
0g
0h
0j
#40000000
b1100 !
b0101 "
b0010 #
1%
b1100 &
b0101 '
b0010 )
1*
b101 +
1-
0/
10
11
13
15
16
19
0:
1;
1>
1?
1H
1J
1L
0O
1P
0Q
1R
1T
0V
1W
0Y
0Z
1\
1^
0_
1`
1a
1c
1d
1f
1h
1i
0j
1k
#42000000
b0111 !
b1000 "
b0000 #
1%
b0111 &
b1000 '
b0000 )
1*
b111 +
1,
0-
14
05
1<
0?
1@
1A
1C
1D
1F
1I
0J
1K
0M
1N
0O
1P
1Q
0R
1S
0U
1V
0W
1X
1Y
0Z
1[
0\
1]
1^
0_
1`
1c
0d
1e
1h
0j
1k
#44000000
b0010 !
b1111 "
b0010 #
b0010 &
b1111 '
b0010 )
0,
1-
04
15
1=
1?
0A
1B
0C
1E
0F
1G
0I
1J
0K
0L
1M
0T
1U
#46000000
b0000 !
b0110 "
b0111 #
0%
b0000 &
b0110 '
b0111 )
0*
b000 +
0-
1/
00
01
03
05
06
09
1:
0;
0<
0>
1?
0@
1A
0B
0C
0D
1F
0G
0H
1I
1J
0K
0N
1O
0P
0S
0X
1Z
0[
0]
0^
0_
0`
0a
0c
0e
0f
0h
0i
0j
0k
#48000000
b0011 !
b1000 "
b1100 #
b0011 &
b1000 '
b1100 )
b011 +
1,
0/
10
11
13
14
16
19
0:
1;
1<
0=
1>
0?
1@
1C
1D
0E
1H
0J
1K
0M
1N
1O
0Q
0U
0V
1X
0Y
1Z
1]
1_
1a
1e
1f
1i
1j
#50000000
b0100 !
b0011 "
b1000 #
b0100 &
b0011 '
b1000 )
b111 +
0,
1-
04
15
0<
1=
0D
1E
1L
0O
1P
1Q
1S
1T
1V
1Y
0Z
1[
0]
1^
1_
0a
0e
0f
1h
0i
1j
#52000000
b1000 !
b1100 "
b0101 #
1%
b1000 &
b1100 '
b0101 )
1*
b000 +
0-
1/
00
01
03
05
06
09
1:
0;
0=
0>
0?
0@
0A
0C
0E
0F
0H
0I
0J
0K
0L
1M
0N
1O
0P
0S
0T
1U
0X
1Z
0[
1\
1]
0^
0_
1`
1b
1d
1e
1g
0h
0j
#54000000
b0100 !
b0101 "
b1010 #
0%
b0100 &
b0101 '
b1010 )
0*
b101 +
1-
0/
10
11
13
15
16
19
0:
1;
1>
1?
1H
1J
1L
0O
1P
0Q
1R
1T
0V
1W
0Y
0Z
0\
0]
1^
1_
0`
0b
0d
0e
0g
1h
1j
#56000000
b1100 "
b0001 #
1%
b1100 '
b0001 )
1*
b100 +
0-
1/
00
01
03
05
06
09
1:
0;
0>
0?
0H
0J
1]
0_
1`
1a
1c
1e
1f
1i
0j
1k
#58000000
b1010 !
b1011 "
b0110 #
b1010 &
b1011 '
b0110 )
b011 +
1-
0/
10
11
13
15
16
19
0:
1;
1<
1=
1>
1?
1@
1B
1D
1E
1G
1H
1J
0L
0M
1N
1O
0P
0R
0T
0U
0W
1X
1Z
1\
0^
0_
0a
1b
0c
1d
0f
1g
0h
0i
0j
0k
#60000000
b0100 !
b0111 "
b1100 #
0%
b0100 &
b0111 '
b1100 )
0*
b111 +
0<
0?
1@
1A
0B
1C
0D
1F
0G
1I
0J
1K
1L
1M
1N
1O
1P
1R
1T
1U
1W
1X
1Z
0\
0]
1^
1_
0`
0b
0d
0e
0g
1h
1j
#62000000
b0101 !
b0110 "
b0101 &
b0110 '
1,
0-
14
05
#64000000
b1000 !
b1000 "
b0001 #
1%
b1000 &
b1000 '
b0001 )
1*
b000 +
0,
1/
00
01
03
04
06
09
1:
0;
0=
0>
0?
0@
0A
0C
0E
0F
0H
0I
0J
0K
0L
0M
0N
0O
0P
0R
0T
0U
0W
0X
0Z
1\
1]
0^
0_
1`
1b
1d
1e
1g
0h
0j
#66000000
b1101 !
b0111 "
b0101 #
1%
b1101 &
b0111 '
b0101 )
1*
b111 +
1,
1-
10
12
14
15
17
1=
1>
0?
1@
1A
1C
1E
1F
1H
1I
0J
1K
1L
1M
1N
1O
1P
1R
1T
1U
1W
1X
1Z
0]
1^
0_
1`
1a
0b
1c
0e
1f
0g
1h
1i
0j
1k
#68000000
b1100 !
b0000 "
b1101 #
0%
b1100 &
b0000 '
b1101 )
0*
b000 +
0,
0-
00
02
04
05
07
0=
0>
0?
0@
0A
0C
0E
0F
0H
0I
0J
0K
0M
0N
1O
0P
1Q
0R
0S
0U
1V
0W
0X
1Y
1Z
0[
0^
1_
0`
0c
0h
1j
0k
#70000000
b0110 !
b1111 "
b0110 #
1%
b0110 &
b1111 '
b0110 )
1*
b111 +
1-
0/
10
11
13
15
16
19
0:
1;
1<
1=
1>
1?
1@
1B
1D
1E
1G
1H
1J
1M
1N
1O
1P
0Q
1R
1U
0V
1W
1X
0Y
1Z
0\
1]
1^
0_
1`
1c
0d
1e
1h
0j
1k
#72000000
b1010 !
b0111 "
b0010 #
1%
b1010 &
b0111 '
b0010 )
1*
b111 +
0L
0O
1P
1Q
0R
1S
0T
1V
0W
1Y
0Z
1[
1\
0]
1^
0_
1`
1c
1d
0e
1h
0j
1k
#74000000
b0101 !
b1111 "
b0101 #
b0101 &
b1111 '
b0101 )
b111 +
1,
1/
01
12
03
14
06
17
09
1:
0;
0<
0?
1@
1A
0B
1C
0D
1F
0G
1I
0J
1K
1L
1N
1O
0Q
1R
0S
1T
0V
1W
1X
0Y
1Z
0[
0\
1]
0d
1e
#76000000
b1011 !
b1000 "
b0100 #
b1011 &
b1000 '
b0100 )
b011 +
0-
0/
10
11
02
13
05
16
07
19
0:
1;
1<
0=
1>
0?
1@
1C
1D
0E
1H
0J
1K
0L
0M
1N
1O
0P
0R
0T
0U
0W
1X
1Z
1\
0^
0_
0a
1b
0c
1d
0f
1g
0h
0i
0j
0k
#78000000
b0010 !
b1100 "
b1111 #
0%
b0010 &
b1100 '
b1111 )
0*
b000 +
0,
1/
00
01
03
04
06
09
1:
0;
0>
1?
0@
0C
0H
1J
0K
1M
0N
1O
0P
1Q
0S
1U
1V
0X
1Y
1Z
0[
0\
0^
1_
0`
1a
0b
0c
0d
1f
0g
0h
1i
1j
0k
#80000000
b0110 !
b1110 "
b0101 #
1%
b0110 &
b1110 '
b0101 )
1*
b110 +
1=
0?
1@
0A
1B
1E
0F
1G
0I
0J
1L
1N
1O
1P
0Q
1R
1T
0V
1W
1X
0Y
1Z
1^
0_
1`
1c
1h
0j
1k
#82000000
b0111 !
b0011 "
b1011 #
0%
b0111 &
b0011 '
b1011 )
0*
b111 +
1,
1-
10
12
14
15
17
1>
1?
1H
1J
0M
0O
1P
1Q
0R
1S
0U
1V
0W
1Y
0Z
1[
0]
1^
1_
0`
0a
0c
0e
0f
1h
0i
1j
0k
#84000000
b1010 !
b0010 "
b1101 #
0%
b1010 &
b0010 '
b1101 )
0*
b010 +
0,
0-
00
02
04
05
07
0>
0?
0H
0J
0L
1O
0P
0Q
0S
0T
0V
0Y
1Z
0[
1\
0^
1_
0`
1a
0c
1d
1f
0h
1i
1j
0k
#86000000
b0100 !
b0100 "
b1001 #
b0100 &
b0100 '
b1001 )
b100 +
0<
0=
0@
0B
0D
0E
0G
1L
1M
0N
0O
1P
1R
1T
1U
1W
0X
0Z
0\
1^
1_
0a
0d
0f
1h
0i
1j
#88000000
b1011 !
b0101 "
b0001 #
1%
b1011 &
b0101 '
b0001 )
1*
b111 +
1,
1-
10
12
14
15
17
1<
1>
0?
1@
1A
1C
1D
1F
1H
1I
0J
1K
0L
1N
0O
1P
1Q
0R
1S
0T
1V
0W
1X
1Y
0Z
1[
1\
1^
0_
1`
1a
1c
1d
1f
1h
1i
0j
1k
#90000000
b0101 !
b0001 "
b0111 #
0%
b0101 &
b0001 '
b0111 )
0*
b001 +
0<
1?
0@
0A
0C
0D
0F
0I
1J
0K
1L
0M
0N
1O
0P
0S
1T
0U
0X
1Z
0[
0\
0^
0_
0`
0a
0c
0d
0f
0h
0i
0j
0k
#92000000
b0000 !
b0111 "
b1000 #
b0000 &
b0111 '
b1000 )
b111 +
0,
0/
10
11
02
13
04
16
07
19
0:
1;
1=
1>
0?
1@
1A
1C
1E
1F
1H
1I
0J
1K
0L
1M
1N
0O
1P
1S
0T
1U
1X
0Z
1[
1^
1_
1h
1j
#94000000
b1001 !
b1010 "
b0100 #
1%
b1001 &
b1010 '
b0100 )
1*
b011 +
1,
0-
14
05
0M
1O
0P
0Q
0S
0U
0V
0Y
1Z
0[
1\
1]
0^
0_
1`
1b
1d
1e
1g
0h
0j
#96000000
b0110 !
b1100 "
b0011 #
1%
b0110 &
b1100 '
b0011 )
1*
b100 +
0,
1/
00
01
03
04
06
09
1:
0;
1<
0=
0>
1?
0@
0C
1D
0E
0H
1J
0K
1L
1M
0N
0O
1P
1R
1T
1U
1W
0X
0Z
0\
1^
0_
1`
1a
0b
1c
0d
1f
0g
1h
1i
0j
1k
#98000000
b0001 !
b0111 "
b1001 #
0%
b0001 &
b0111 '
b1001 )
0*
b111 +
1,
1-
10
12
14
15
17
0<
1=
1>
0?
1@
1C
0D
1E
1H
0J
1K
0L
1N
0O
1P
1Q
0R
1S
0T
1V
0W
1X
1Y
0Z
1[
0]
1^
1_
0`
0a
0c
0e
0f
1h
0i
1j
0k
#100000000
b0111 !
b1111 #
b0111 &
b1111 )
1<
1?
0A
1B
0C
1D
0F
1G
0I
1J
0K
1L
1O
0Q
1R
0S
1T
0V
1W
0Y
1Z
0[
#102000000
b1001 !
b1000 "
b0010 #
1%
b1001 &
b1000 '
b0010 )
1*
b001 +
0-
0/
10
11
02
13
05
16
07
19
0:
1;
0<
0=
1>
1?
0@
0B
0D
0E
0G
1H
1J
0L
0M
0N
0O
0P
0R
0T
0U
0W
0X
0Z
1\
1]
0^
0_
1`
1b
1d
1e
1g
0h
0j
#104000000
b1100 !
b0110 "
b0011 #
1%
b1100 &
b0110 '
b0011 )
1*
b100 +
0,
1/
00
01
03
04
06
09
1:
0;
1=
0>
1?
0@
1A
0C
1E
1F
0H
1I
1J
0K
1L
1M
0N
0O
1P
1R
1T
1U
1W
0X
0Z
0]
1^
0_
1`
1a
0b
1c
0e
1f
0g
1h
1i
0j
1k
#106000000
b0101 !
b1000 "
b1110 #
0%
b0101 &
b1000 '
b1110 )
0*
b001 +
1,
0/
10
11
13
14
16
19
0:
1;
0=
1>
1?
0A
0E
0F
1H
0I
1J
0M
1O
0P
1Q
0R
0U
1V
0W
1Y
1Z
0\
1]
0^
1_
0`
0c
0d
1e
0h
1j
0k
#108000000
b0100 !
b0101 "
b1010 #
b0100 &
b0101 '
b1010 )
b101 +
0,
1-
04
15
1M
0O
1P
0Q
1R
1U
0V
1W
0Y
0Z
0]
1^
1_
0a
0e
0f
1h
0i
1j
#110000000
b0000 !
b0010 "
b0011 #
b0000 &
b0010 '
b0011 )
b000 +
0-
1/
00
01
03
05
06
09
1:
0;
1=
0>
1?
0@
1A
0C
1E
1F
0H
1I
1J
0K
0L
0M
0N
0O
0P
0R
0T
0U
0W
0X
0Z
0^
0_
0h
0j
#112000000
b0011 !
b0000 "
b0100 #
b0011 &
b0000 '
b0100 )
b011 +
1,
0/
10
11
13
14
16
19
0:
1;
1<
0=
1>
0?
1@
1C
1D
0E
1H
0J
1K
1N
1O
1X
1Z
#114000000
b0101 !
b1010 "
b0000 #
1%
b0101 &
b1010 '
b0000 )
1*
b111 +
0<
1=
0D
1E
1L
0O
1P
1Q
1S
1T
1V
1Y
0Z
1[
1]
1^
0_
1`
1a
1c
1e
1f
1h
1i
0j
1k
#116000000
b1011 !
b1011 "
b0111 #
b1011 &
b1011 '
b0111 )
b011 +
1-
1/
01
12
03
15
06
17
09
1:
0;
1<
1?
0A
1B
0C
1D
0F
1G
0I
1J
0K
0L
1O
0P
0Q
0S
0T
0V
0Y
1Z
0[
1\
0^
0_
0a
1b
0c
1d
0f
1g
0h
0i
0j
0k
#118000000
b0001 !
b1100 "
b1110 #
0%
b0001 &
b1100 '
b1110 )
0*
b001 +
0-
0/
10
11
02
13
05
16
07
19
0:
1;
0<
0=
1>
1?
0@
0B
0D
0E
0G
1H
1J
1M
0N
1O
0P
1Q
0S
1U
1V
0X
1Y
1Z
0[
0\
0^
1_
0`
1a
0b
0c
0d
1f
0g
0h
1i
1j
0k
#120000000
b0101 !
b0111 "
b1101 #
b0101 &
b0111 '
b1101 )
b111 +
1-
1/
01
12
03
15
06
17
09
1:
0;
1=
0?
1@
1A
1C
1E
1F
1I
0J
1K
1L
1N
1O
1P
0Q
1R
1T
0V
1W
1X
0Y
1Z
0]
1^
1_
0a
0e
0f
1h
0i
1j
#122000000
b1011 !
b1100 "
b1000 #
1%
b1011 &
b1100 '
b1000 )
1*
b111 +
0-
0/
10
11
02
13
05
16
07
19
0:
1;
1<
0=
1>
0?
1@
1C
1D
0E
1H
0J
1K
0L
1N
0O
1P
1Q
0R
1S
0T
1V
0W
1X
1Y
0Z
1[
1\
1]
1^
1_
1`
1b
1d
1e
1g
1h
1j
#124000000
b0010 !
b0010 "
b0101 #
0%
b0010 &
b0010 '
b0101 )
0*
b010 +
0,
1/
00
01
03
04
06
09
1:
0;
1=
0>
0?
0A
1B
0C
1E
0F
1G
0H
0I
0J
0K
0M
1O
0P
0Q
0S
0U
0V
0Y
1Z
0[
0\
0]
0^
0_
0`
0b
0d
0e
0g
0h
0j
#126000000
b1000 !
b0110 "
b1111 #
0%
b1000 &
b0110 '
b1111 )
0*
b000 +
0<
1?
0@
1A
0B
0D
1F
0G
1I
1J
1M
0N
1O
0P
1Q
0S
1U
1V
0X
1Y
1Z
0[
1\
0^
1_
0`
1a
0c
1d
1f
0h
1i
1j
0k
#128000000
b0110 !
b1100 "
b0011 #
1%
b0110 &
b1100 '
b0011 )
1*
b100 +
1<
0=
1D
0E
1L
0O
1P
0Q
1R
1T
0V
1W
0Y
0Z
0\
1]
1^
0_
1`
1c
0d
1e
1h
0j
1k
#130000000
b1110 !
b0100 "
b1110 &
b0100 '
1\
0]
1d
0e
#132000000
b1011 !
b1011 "
b0111 #
b1011 &
b1011 '
b0111 )
b011 +
1,
1-
10
12
14
15
17
1=
1>
1?
1@
0A
1B
1E
0F
1G
1H
0I
1J
0L
0M
1N
1O
0P
0R
0T
0U
0W
1X
1Z
1]
0^
0_
0a
1b
0c
1e
0f
1g
0h
0i
0j
0k
#134000000
b1001 !
b1101 "
b0111 #
b1001 &
b1101 '
b0111 )
b001 +
0<
0=
0@
0B
0D
0E
0G
1M
0N
1O
0P
1Q
0S
1U
1V
0X
1Y
1Z
0[
0^
0_
0h
0j
#136000000
b0010 !
b0001 "
b0100 #
0%
b0010 &
b0001 '
b0100 )
0*
b011 +
0,
0/
10
11
02
13
04
16
07
19
0:
1;
1<
1>
0?
1@
1A
1C
1D
1F
1H
1I
0J
1K
0M
1N
1O
0Q
0U
0V
1X
0Y
1Z
0\
0]
0`
0b
0d
0e
0g
#138000000
b1100 !
b0101 "
b0010 #
1%
b1100 &
b0101 '
b0010 )
1*
b101 +
0<
1?
0@
0A
0C
0D
0F
0I
1J
0K
1L
1M
0N
0O
1P
1R
1T
1U
1W
0X
0Z
1\
1^
0_
1`
1a
1c
1d
1f
1h
1i
0j
1k
#140000000
b0001 "
b1110 #
0%
b0001 '
b1110 )
0*
b001 +
0M
1O
0P
1Q
0R
0U
1V
0W
1Y
1Z
0^
1_
0`
0c
0h
1j
0k
#142000000
b0110 !
b0100 "
b1011 #
b0110 &
b0100 '
b1011 )
b100 +
0-
1/
00
01
03
05
06
09
1:
0;
1<
0>
1?
0@
1A
0C
1D
1F
0H
1I
1J
0K
1M
0N
0O
1P
0Q
1R
1U
0V
1W
0X
0Y
0Z
0\
1^
1_
0a
0d
0f
1h
0i
1j
#144000000
b0001 !
b1010 "
b1100 #
0%
b0001 &
b1010 '
b1100 )
0*
b011 +
1,
0/
10
11
13
14
16
19
0:
1;
0<
1=
1>
0?
1@
1C
0D
1E
1H
0J
1K
0L
0M
1N
1O
0P
0R
0T
0U
0W
1X
1Z
1]
0^
1_
0`
1a
0c
1e
1f
0h
1i
1j
0k
#146000000
b0000 !
b0011 "
b0100 #
b0000 &
b0011 '
b0100 )
0,
1-
04
15
0]
0_
0a
0e
0f
0i
0j
#148000000
b0110 !
b1100 "
b0011 #
1%
b0110 &
b1100 '
b0011 )
1*
b100 +
0-
1/
00
01
03
05
06
09
1:
0;
1<
0=
0>
1?
0@
0C
1D
0E
0H
1J
0K
1L
1M
0N
0O
1P
1R
1T
1U
1W
0X
0Z
1]
1^
0_
1`
1a
1c
1e
1f
1h
1i
0j
1k
#150000000
b0011 "
b1010 #
0%
b0011 '
b1010 )
0*
b111 +
1-
0/
10
11
13
15
16
19
0:
1;
1=
1>
1?
1@
0A
1B
1E
0F
1G
1H
0I
1J
0M
1N
0O
1P
1Q
0R
1S
0U
1V
0W
1X
1Y
0Z
1[
0]
1^
1_
0`
0a
0c
0e
0f
1h
0i
1j
0k
#152000000
b1101 !
b0110 "
b0100 #
1%
b1101 &
b0110 '
b0100 )
1*
b111 +
1,
0-
14
05
0<
0?
1@
1A
0B
1C
0D
1F
0G
1I
0J
1K
1M
1N
1O
0Q
1R
0S
1U
0V
1W
1X
0Y
1Z
0[
1\
0_
1`
1a
1c
1d
1f
1i
0j
1k
#154000000
b0101 !
b1001 "
b1111 #
0%
b0101 &
b1001 '
b1111 )
0*
b001 +
1-
1/
01
12
03
15
06
17
09
1:
0;
0=
1?
0@
0A
0C
0E
0F
0I
1J
0K
0M
0N
1O
0P
1Q
0R
0S
0U
1V
0W
0X
1Y
1Z
0[
0\
1]
0^
1_
0`
0c
0d
1e
0h
1j
0k
