3_EXE/alu.vhdl
library IEEE; 
use IEEE.std_logic_1164.all;
use ieee.numeric_std.all;

entity Alu is
  port ( op1  : in  Std_Logic_Vector(31 downto 0);
         op2  : in  Std_Logic_Vector(31 downto 0);
         cin  : in  Std_Logic;
         cmd  : in  Std_Logic_Vector(1 downto 0);
         res  : out Std_Logic_Vector(31 downto 0);
         cout : out Std_Logic;
         z    : out Std_Logic;
         n    : out Std_Logic;
         v    : out Std_Logic;
         vdd  : in  bit;
         vss  : in  bit );
end Alu;

architecture flow of Alu is
  signal s1: Std_Logic_Vector(32 downto 0);
  signal cout1: Std_Logic;
begin
  res <= s1(31 downto 0);

  z <= '1' when s1 = "000000000000000000000000000000000" 
    else '0';

  n <= s1(31);
  process(cmd, op1, op2, cin, s1, cout1)
  begin
  -- 00 ADD
  -- 01 AND
  -- 10 OR
  -- 11 XOR
  case cmd is
    when "01" =>
      s1 <= "0"&(op1 and op2);
      v <= '0';
      cout <= '0';
    when "10" =>
      s1 <= "0"&(op1 or op2);
      v <= '0';
      cout <= '0';  
    when "11" =>
      s1 <= "0"&(op1 xor op2);
      v <= '0';
      cout <= '0';
    when others =>
      if cin = '0' then s1 <= Std_Logic_Vector( signed("0"&op1) + signed(op2));
      else s1 <= Std_Logic_Vector( signed("0"&op1) + signed(op2) + 1);
      end if;
      cout <= s1(32);
      if op1(31) = '1' and op2(31) = '1' and s1(31) = '0' then 
        v <= '1';
      elsif op1(31) = '0' and op2(31) = '0' and s1(31) = '1' then
        v <= '1';
      else 
        v <= '0';
      end if;
  end case;
  end process;

end flow;

3_EXE/alu_tb.vhdl
library IEEE, work; 
use ieee.math_real.all;
use ieee.numeric_std.all;
use ieee.std_logic_1164.all;
use work.alu;

entity Alu_tb is
end Alu_tb;

architecture test_bench of Alu_tb is
  signal op1, op2, res: std_logic_vector(31 downto 0);
  signal cin, cout, z,n,v:std_logic;
  signal cmd : std_logic_vector(1 downto 0);
  signal vdd, vss: bit;

  begin
    l0 : entity work.Alu(flow)
    port map(op1, op2, cin, cmd, res, cout, z, n, v, vdd, vss);

    process
    -- var for random
    variable seed1 :positive ; 
    variable seed2 :positive ; 
    variable re1 : integer;    
    variable re2 : real ;

    -- var in
    variable rand_1 : unsigned(31 downto 0); -- op1
    variable rand_2 : unsigned(31 downto 0); -- op2
    variable new_val : std_logic_vector(32 downto 0); -- res compute
    variable var_command : unsigned(1 downto 0); -- random command
    variable var_cout : std_logic;
    variable rand_cin : unsigned(0 downto 0);
    begin
      
      for i in 0 to 100 loop

        -- random command
        uniform (seed1,seed2,re2);
        re1 := integer (re2 * real(2**2 -1));
        var_command := to_unsigned (re1,2);


        
        uniform (seed1,seed2,re2);
        re1 := integer (re2 * real(2**30 -1));
        rand_1 := to_unsigned (re1,32);

        uniform (seed1,seed2,re2);
        re1 := integer (re2 * real(2**30 -1));
        rand_2 := to_unsigned (re1,32);

        uniform (seed1,seed2,re2);
        re1 := integer (re2 * real(2**1 -1));
        rand_cin := to_unsigned (re1,1);

        op1 <= std_logic_vector(rand_1);
        op2 <= std_logic_vector(rand_2);
        cin <= std_logic(rand_cin(0));
        cmd <= std_logic_vector(var_command);

        wait for 2 ns;

        -- test result
        case var_command is
        when "01" =>
        new_val := "0"&std_logic_vector(rand_1 and rand_2);
        assert (res = new_val(31 downto 0)) report "ERROR and " severity ERROR;
        --assert (v='0') report "ERROR and v = 1" severity ERROR;
        
        when "10" =>
        new_val := "0"&std_logic_vector(rand_1 or rand_2);
        assert (res = new_val(31 downto 0)) report "ERROR or" severity ERROR;
        
        when "11" =>
        new_val := "0"&std_logic_vector(rand_1 xor rand_2);
        assert (res = new_val(31 downto 0)) report "ERROR xor " severity ERROR;
        
        when others =>
        new_val := std_logic_vector("0"&rand_1 + rand_2 + unsigned'(rand_cin));
        var_cout := new_val(32);
        assert (res = new_val(31 downto 0)) report "Error add" severity ERROR;
        assert (var_cout = cout) report "Error add cout" severity ERROR;
      end case;

    end loop;
    wait;      
  end process;

end test_bench;

3_EXE/alu.vcd
$date
  Wed Jan 23 20:15:48 2019
$end
$version
  GHDL v0
$end
$timescale
  1 fs
$end
$scope module standard $end
$upscope $end
$scope module math_real $end
$upscope $end
$scope module std_logic_1164 $end
$upscope $end
$scope module numeric_std $end
$upscope $end
$scope module alu_tb $end
$var reg 32 ! op1[31:0] $end
$var reg 32 " op2[31:0] $end
$var reg 32 # res[31:0] $end
$var reg 1 $ cin $end
$var reg 1 % cout $end
$var reg 1 & z $end
$var reg 1 ' n $end
$var reg 1 ( v $end
$var reg 2 ) cmd[1:0] $end
$var reg 1 * vdd $end
$var reg 1 + vss $end
$scope module l0 $end
$var reg 32 , op1[31:0] $end
$var reg 32 - op2[31:0] $end
$var reg 1 . cin $end
$var reg 2 / cmd[1:0] $end
$var reg 32 0 res[31:0] $end
$var reg 1 1 cout $end
$var reg 1 2 z $end
$var reg 1 3 n $end
$var reg 1 4 v $end
$var reg 1 5 vdd $end
$var reg 1 6 vss $end
$var reg 33 7 s1[32:0] $end
$var reg 1 8 cout1 $end
$upscope $end
$upscope $end
$enddefinitions $end
#0
b00111110010111101000011110001011 !
b00101001011100000110000001010110 "
b00010111001011101110011111011101 #
0$
0%
0&
0'
0(
b11 )
0*
0+
b00111110010111101000011110001011 ,
b00101001011100000110000001010110 -
0.
b11 /
b00010111001011101110011111011101 0
01
02
03
04
05
06
b000010111001011101110011111011101 7
U8
#2000000
b00001010010110010111110010111111 !
b00101010100010011000101101001000 "
b00110100111000110000100000000111 #
b00 )
b00001010010110010111110010111111 ,
b00101010100010011000101101001000 -
b00 /
b00110100111000110000100000000111 0
b000110100111000110000100000000111 7
#4000000
b00001010101101010010100000100000 !
b00101001111010101101001001010110 "
b00001000101000000000000000000000 #
b01 )
b00001010101101010010100000100000 ,
b00101001111010101101001001010110 -
b01 /
b00001000101000000000000000000000 0
b000001000101000000000000000000000 7
#6000000
b00000111001001100101101111011010 !
b00010011001000110010100110110000 "
b00010100000001010111001001101010 #
b11 )
b00000111001001100101101111011010 ,
b00010011001000110010100110110000 -
b11 /
b00010100000001010111001001101010 0
b000010100000001010111001001101010 7
#8000000
b00111100110100010110110100000101 !
b00000101111000000011100111111010 "
b00111101111100010111110111111111 #
1$
b10 )
b00111100110100010110110100000101 ,
b00000101111000000011100111111010 -
1.
b10 /
b00111101111100010111110111111111 0
b000111101111100010111110111111111 7
#10000000
b00111010100011101111010001101110 !
b00011100001111000100011101000000 "
b00100110101100101011001100101110 #
0$
b11 )
b00111010100011101111010001101110 ,
b00011100001111000100011101000000 -
0.
b11 /
b00100110101100101011001100101110 0
b000100110101100101011001100101110 7
#12000000
b00000101101001010011110110000011 !
b00111010000111111001011000100101 "
b00111111101110101010101110100110 #
b00000101101001010011110110000011 ,
b00111010000111111001011000100101 -
b00111111101110101010101110100110 0
b000111111101110101010101110100110 7
#14000000
b00111000010000000100001110001111 !
b00000000010110001110010010000000 "
b00111000100110010010100000001111 #
b00 )
b00111000010000000100001110001111 ,
b00000000010110001110010010000000 -
b00 /
b00111000100110010010100000001111 0
b000111000100110010010100000001111 7
#16000000
b00110101001000001111010001111010 !
b00000000010101100010000001110001 "
b00110101011101101101010000001011 #
b11 )
b00110101001000001111010001111010 ,
b00000000010101100010000001110001 -
b11 /
b00110101011101101101010000001011 0
b000110101011101101101010000001011 7
#18000000
b00010101110011100010011011010001 !
b00011101100000001011100101001001 "
b00011101110011101011111111011001 #
1$
b10 )
b00010101110011100010011011010001 ,
b00011101100000001011100101001001 -
1.
b10 /
b00011101110011101011111111011001 0
b000011101110011101011111111011001 7
#20000000
b00111110010111111000010000110010 !
b00000000101011011111001101111000 "
b00111111000011010111011110101010 #
0$
b00 )
b00111110010111111000010000110010 ,
b00000000101011011111001101111000 -
0.
b00 /
b00111111000011010111011110101010 0
b000111111000011010111011110101010 7
#22000000
b00100011100010000001111100110010 !
b00010010100101110111100001010110 "
b00000010100000000001100000010010 #
b01 )
b00100011100010000001111100110010 ,
b00010010100101110111100001010110 -
b01 /
b00000010100000000001100000010010 0
b000000010100000000001100000010010 7
#24000000
b00110010101000111100100101111110 !
b00010001001101010111010110100101 "
b00110011101101111111110111111111 #
b10 )
b00110010101000111100100101111110 ,
b00010001001101010111010110100101 -
b10 /
b00110011101101111111110111111111 0
b000110011101101111111110111111111 7
#26000000
b00110010011101110100001010111000 !
b00101100010001011001101110100000 "
b00100000010001010000001010100000 #
1$
b01 )
b00110010011101110100001010111000 ,
b00101100010001011001101110100000 -
1.
b01 /
b00100000010001010000001010100000 0
b000100000010001010000001010100000 7
#28000000
b00011100110100000010101011001100 !
b00010111001111111110101010000100 "
b00010100000100000010101010000100 #
0$
b00011100110100000010101011001100 ,
b00010111001111111110101010000100 -
0.
b00010100000100000010101010000100 0
b000010100000100000010101010000100 7
#30000000
b00100001111000000010001000100010 !
b00111000001010001011011101001000 "
b00111001111010001011011101101010 #
b10 )
b00100001111000000010001000100010 ,
b00111000001010001011011101001000 -
b10 /
b00111001111010001011011101101010 0
b000111001111010001011011101101010 7
#32000000
b00000010000011011101011100001101 !
b00011010010010100000110110110010 "
b00011010010011111101111110111111 #
1$
b00000010000011011101011100001101 ,
b00011010010010100000110110110010 -
1.
b00011010010011111101111110111111 0
b000011010010011111101111110111111 7
#34000000
b00011100100101101010111100101001 !
b00010100101101111100011000010000 "
b00011100101101111110111100111001 #
b00011100100101101010111100101001 ,
b00010100101101111100011000010000 -
b00011100101101111110111100111001 0
b000011100101101111110111100111001 7
#36000000
b00100010100000001111000101000101 !
b00001010011001110011100001001010 "
b00101010111001111111100101001111 #
b00100010100000001111000101000101 ,
b00001010011001110011100001001010 -
b00101010111001111111100101001111 0
b000101010111001111111100101001111 7
#38000000
b00111101000101110011110100011010 !
b00011110100000111000011000100000 "
b00011100000000110000010000000000 #
0$
b01 )
b00111101000101110011110100011010 ,
b00011110100000111000011000100000 -
0.
b01 /
b00011100000000110000010000000000 0
b000011100000000110000010000000000 7
#40000000
b00000110111010101010011011101010 !
b00010011000001010001001110001110 "
b00010111111011111011011111101110 #
b10 )
b00000110111010101010011011101010 ,
b00010011000001010001001110001110 -
b10 /
b00010111111011111011011111101110 0
b000010111111011111011011111101110 7
#42000000
b00010101000010010110110000111101 !
b00010110000101001110011011001001 "
b00010111000111011110111011111101 #
b00010101000010010110110000111101 ,
b00010110000101001110011011001001 -
b00010111000111011110111011111101 0
b000010111000111011110111011111101 7
#44000000
b00011111111100000110011000111101 !
b00100100011111100010010101000100 "
b01000100011011101000101110000010 #
1$
b00 )
b00011111111100000110011000111101 ,
b00100100011111100010010101000100 -
1.
b00 /
b01000100011011101000101110000010 0
b001000100011011101000101110000010 7
#46000000
b00110101001100111110000101110001 !
b00000100101101001111001100111100 "
b00000100001100001110000100110000 #
0$
b01 )
b00110101001100111110000101110001 ,
b00000100101101001111001100111100 -
0.
b01 /
b00000100001100001110000100110000 0
b000000100001100001110000100110000 7
#48000000
b00011011110110010010100010001111 !
b00101000010101101001000000101110 "
b00001000010100000000000000001110 #
1$
b00011011110110010010100010001111 ,
b00101000010101101001000000101110 -
1.
b00001000010100000000000000001110 0
b000001000010100000000000000001110 7
#50000000
b00011001011010111111001010001100 !
b00010111000110011001011110010010 "
b00011111011110111111011110011110 #
b10 )
b00011001011010111111001010001100 ,
b00010111000110011001011110010010 -
b10 /
b00011111011110111111011110011110 0
b000011111011110111111011110011110 7
#52000000
b00010101101101010011110101010100 !
b00000001100110111011001001001111 "
b00000001100100010011000001000100 #
0$
b01 )
b00010101101101010011110101010100 ,
b00000001100110111011001001001111 -
0.
b01 /
b00000001100100010011000001000100 0
b000000001100100010011000001000100 7
#54000000
b00000001011011000010010000001001 !
b00010110110001111111100011101010 "
b00000000010001000010000000001000 #
1$
b00000001011011000010010000001001 ,
b00010110110001111111100011101010 -
1.
b00000000010001000010000000001000 0
b000000000010001000010000000001000 7
#56000000
b00101101110110110111000100001001 !
b00000011111000010011010110001000 "
b00101111111110110111010110001001 #
b10 )
b00101101110110110111000100001001 ,
b00000011111000010011010110001000 -
b10 /
b00101111111110110111010110001001 0
b000101111111110110111010110001001 7
#58000000
b00011100111011000000010001111111 !
b00101111100101001111000111000110 "
b00001100100001000000000001000110 #
b01 )
b00011100111011000000010001111111 ,
b00101111100101001111000111000110 -
b01 /
b00001100100001000000000001000110 0
b000001100100001000000000001000110 7
#60000000
b00001000100001100000001111100101 !
b00100010110100010000010011011001 "
b00101011010101110000100010111110 #
0$
b00 )
b00001000100001100000001111100101 ,
b00100010110100010000010011011001 -
0.
b00 /
b00101011010101110000100010111110 0
b000101011010101110000100010111110 7
#62000000
b00110011110101011101000111011001 !
b00111010001101000110000001000100 "
b00110010000101000100000001000000 #
b01 )
b00110011110101011101000111011001 ,
b00111010001101000110000001000100 -
b01 /
b00110010000101000100000001000000 0
b000110010000101000100000001000000 7
#64000000
b00101101001000111011011000010001 !
b00100111101111111111110101001000 "
b00101111101111111111111101011001 #
1$
b10 )
b00101101001000111011011000010001 ,
b00100111101111111111110101001000 -
1.
b10 /
b00101111101111111111111101011001 0
b000101111101111111111111101011001 7
#66000000
b00000010011001111001111101111110 !
b00110011111001100111110111000011 "
b00110110010011100001110101000001 #
0$
b00 )
b00000010011001111001111101111110 ,
b00110011111001100111110111000011 -
0.
b00 /
b00110110010011100001110101000001 0
b000110110010011100001110101000001 7
#68000000
b00000010100011000001111001010000 !
b00011001011111101101001010110100 "
b00011011111111101101111011110100 #
b10 )
b00000010100011000001111001010000 ,
b00011001011111101101001010110100 -
b10 /
b00011011111111101101111011110100 0
b000011011111111101101111011110100 7
#70000000
b00101001011001101100100100010011 !
b00000001011010011110100001111000 "
b00101010110100001011000110001011 #
b00 )
b00101001011001101100100100010011 ,
b00000001011010011110100001111000 -
b00 /
b00101010110100001011000110001011 0
b000101010110100001011000110001011 7
#72000000
b00110100010110011001010010101011 !
b00010111100000100101101100001001 "
b00010100000000000001000000001001 #
b01 )
b00110100010110011001010010101011 ,
b00010111100000100101101100001001 -
b01 /
b00010100000000000001000000001001 0
b000010100000000000001000000001001 7
#74000000
b00011001101010110110110111100000 !
b00010101110101111110100110010000 "
b00001100011111001000010001110000 #
1$
b11 )
b00011001101010110110110111100000 ,
b00010101110101111110100110010000 -
1.
b11 /
b00001100011111001000010001110000 0
b000001100011111001000010001110000 7
#76000000
b00011101001000011000010010100100 !
b00000001001000110100100101011111 "
b00000001001000010000000000000100 #
0$
b01 )
b00011101001000011000010010100100 ,
b00000001001000110100100101011111 -
0.
b01 /
b00000001001000010000000000000100 0
b000000001001000010000000000000100 7
#78000000
b00111100100010100110001100111000 !
b00110011000111101110001001101011 "
b00110000000010100110001000101000 #
b00111100100010100110001100111000 ,
b00110011000111101110001001101011 -
b00110000000010100110001000101000 0
b000110000000010100110001000101000 7
#80000000
b00110101100001010110010001011000 !
b00011110110011111100101001000011 "
b00101011010010101010111000011011 #
1$
b11 )
b00110101100001010110010001011000 ,
b00011110110011111100101001000011 -
1.
b11 /
b00101011010010101010111000011011 0
b000101011010010101010111000011011 7
#82000000
b00111011100011011111011001110111 !
b00111110101100101001010100001000 "
b00111111101111111111011101111111 #
0$
b10 )
b00111011100011011111011001110111 ,
b00111110101100101001010100001000 -
0.
b10 /
b00111111101111111111011101111111 0
b000111111101111111111011101111111 7
#84000000
b00000011110001011100010000111010 !
b00010001111101100110011001011111 "
b00000001110001000100010000011010 #
b01 )
b00000011110001011100010000111010 ,
b00010001111101100110011001011111 -
b01 /
b00000001110001000100010000011010 0
b000000001110001000100010000011010 7
#86000000
b00111101001111011101001011110011 !
b00101111111001111111011101101010 "
b00101101001001011101001001100010 #
b00111101001111011101001011110011 ,
b00101111111001111111011101101010 -
b00101101001001011101001001100010 0
b000101101001001011101001001100010 7
#88000000
b00110001110011010010110110010100 !
b00000101101100011010111111101110 "
b00110101111111011010111111111110 #
1$
b10 )
b00110001110011010010110110010100 ,
b00000101101100011010111111101110 -
1.
b10 /
b00110101111111011010111111111110 0
b000110101111111011010111111111110 7
#90000000
b00001000100101100000000001000010 !
b00010011100111110011100011110111 "
b00011100001101010011100100111010 #
b00 )
b00001000100101100000000001000010 ,
b00010011100111110011100011110111 -
b00 /
b00011100001101010011100100111010 0
b000011100001101010011100100111010 7
#92000000
b00000110000000111000111100111011 !
b00100111000100110100010110000100 "
b00100111000100111100111110111111 #
0$
b10 )
b00000110000000111000111100111011 ,
b00100111000100110100010110000100 -
0.
b10 /
b00100111000100111100111110111111 0
b000100111000100111100111110111111 7
#94000000
b00000110001101110100110110101111 !
b00101010110110010100111010111011 "
b00000010000100010100110010101011 #
1$
b01 )
b00000110001101110100110110101111 ,
b00101010110110010100111010111011 -
1.
b01 /
b00000010000100010100110010101011 0
b000000010000100010100110010101011 7
#96000000
b00011000011100001010110100101011 !
b00001101001001101111100110110010 "
b00001000001000001010100100100010 #
b00011000011100001010110100101011 ,
b00001101001001101111100110110010 -
b00001000001000001010100100100010 0
b000001000001000001010100100100010 7
#98000000
b00011001011111000001101100000001 !
b00000011011100010111110111011101 "
b00000001011100000001100100000001 #
b00011001011111000001101100000001 ,
b00000011011100010111110111011101 -
b00000001011100000001100100000001 0
b000000001011100000001100100000001 7
#100000000
b00100001010111110111011111000101 !
b00101010010010111011001000001001 "
b01001011101010110010100111001110 #
0$
b00 )
b00100001010111110111011111000101 ,
b00101010010010111011001000001001 -
0.
b00 /
b01001011101010110010100111001110 0
b001001011101010110010100111001110 7
#102000000
b00011111110000100001001100111011 !
b00011000100101000100101001011011 "
b00011000100000000000001000011011 #
b01 )
b00011111110000100001001100111011 ,
b00011000100101000100101001011011 -
b01 /
b00011000100000000000001000011011 0
b000011000100000000000001000011011 7
#104000000
b00001000010010001011111111100111 !
b00110010100101011100100110100111 "
b00111010110111011111111111100111 #
1$
b10 )
b00001000010010001011111111100111 ,
b00110010100101011100100110100111 -
1.
b10 /
b00111010110111011111111111100111 0
b000111010110111011111111111100111 7
#106000000
b00010100000001110110000111011100 !
b00110000100110001011110001111100 "
b00110100100111111111110111111100 #
0$
b00010100000001110110000111011100 ,
b00110000100110001011110001111100 -
0.
b00110100100111111111110111111100 0
b000110100100111111111110111111100 7
#108000000
b00110101110110111011010000011101 !
b00101001101110000001000100010101 "
b00100001100110000001000000010101 #
b01 )
b00110101110110111011010000011101 ,
b00101001101110000001000100010101 -
b01 /
b00100001100110000001000000010101 0
b000100001100110000001000000010101 7
#110000000
b00001101000110110001111000001100 !
b00100110010011110101101100001000 "
b00101111010111110101111100001100 #
b10 )
b00001101000110110001111000001100 ,
b00100110010011110101101100001000 -
b10 /
b00101111010111110101111100001100 0
b000101111010111110101111100001100 7
#112000000
b00001110110110101111000001101110 !
b00110011000001001010110110110010 "
b00111111110111101111110111111110 #
b00001110110110101111000001101110 ,
b00110011000001001010110110110010 -
b00111111110111101111110111111110 0
b000111111110111101111110111111110 7
#114000000
b00100010111011011110100010110001 !
b00110011010001000001010001100101 "
b00100010010001000000000000100001 #
b01 )
b00100010111011011110100010110001 ,
b00110011010001000001010001100101 -
b01 /
b00100010010001000000000000100001 0
b000100010010001000000000000100001 7
#116000000
b00110011000010111100100011101101 !
b00010111011010110111010001111011 "
b00110111011010111111110011111111 #
1$
b10 )
b00110011000010111100100011101101 ,
b00010111011010110111010001111011 -
1.
b10 /
b00110111011010111111110011111111 0
b000110111011010111111110011111111 7
#118000000
b00100100101011100011010001111101 !
b00111011010101110101001101010011 "
b00100000000001100001000001010001 #
0$
b01 )
b00100100101011100011010001111101 ,
b00111011010101110101001101010011 -
0.
b01 /
b00100000000001100001000001010001 0
b000100000000001100001000001010001 7
#120000000
b00001100000001110000101110010111 !
b00110101110011110101001101011100 "
b01000001110101100101111011110100 #
1$
b00 )
b00001100000001110000101110010111 ,
b00110101110011110101001101011100 -
1.
b00 /
b01000001110101100101111011110100 0
b001000001110101100101111011110100 7
#122000000
b00000110111010000001001111011011 !
b00001101010001110000100001010110 "
b00001111111011110001101111011111 #
0$
b10 )
b00000110111010000001001111011011 ,
b00001101010001110000100001010110 -
0.
b10 /
b00001111111011110001101111011111 0
b000001111111011110001101111011111 7
#124000000
b00110001001100101010111011011100 !
b00100010010111000011000110000001 "
b00010011011011101001111101011101 #
1$
b11 )
b00110001001100101010111011011100 ,
b00100010010111000011000110000001 -
1.
b11 /
b00010011011011101001111101011101 0
b000010011011011101001111101011101 7
#126000000
b00011011100011101000011101000011 !
b00000111101011100010101011110001 "
b00011111101011101010111111110011 #
0$
b10 )
b00011011100011101000011101000011 ,
b00000111101011100010101011110001 -
0.
b10 /
b00011111101011101010111111110011 0
b000011111101011101010111111110011 7
#128000000
b00101100111110111110111111101111 !
b00011111000000110110011001101101 "
b00001100000000110110011001101101 #
b01 )
b00101100111110111110111111101111 ,
b00011111000000110110011001101101 -
b01 /
b00001100000000110110011001101101 0
b000001100000000110110011001101101 7
#130000000
b00010111011000000000011011100111 !
b00011010010010111011101011001011 "
b00011111011010111011111011101111 #
b10 )
b00010111011000000000011011100111 ,
b00011010010010111011101011001011 -
b10 /
b00011111011010111011111011101111 0
b000011111011010111011111011101111 7
#132000000
b00011100010111001100100000111011 !
b00001110111000100111101001110100 "
b00011110111111101111101001111111 #
b00011100010111001100100000111011 ,
b00001110111000100111101001110100 -
b00011110111111101111101001111111 0
b000011110111111101111101001111111 7
#134000000
b00100100101010001101110000000111 !
b00000010000111110000010111101010 "
b00100110101101111101100111101101 #
1$
b11 )
b00100100101010001101110000000111 ,
b00000010000111110000010111101010 -
1.
b11 /
b00100110101101111101100111101101 0
b000100110101101111101100111101101 7
#136000000
b00101010011000100001000100011000 !
b00111011101111000010100001000111 "
b00101010001000000000000000000000 #
0$
b01 )
b00101010011000100001000100011000 ,
b00111011101111000010100001000111 -
0.
b01 /
b00101010001000000000000000000000 0
b000101010001000000000000000000000 7
#138000000
b00111100011111110101010010101100 !
b00000110001100100110111011011111 "
b00111110011111110111111011111111 #
1$
b10 )
b00111100011111110101010010101100 ,
b00000110001100100110111011011111 -
1.
b10 /
b00111110011111110111111011111111 0
b000111110011111110111111011111111 7
#140000000
b00100110010110110000011000011011 !
b00000011010011101111010000011111 "
b00100101000101011111001000000100 #
b11 )
b00100110010110110000011000011011 ,
b00000011010011101111010000011111 -
b11 /
b00100101000101011111001000000100 0
b000100101000101011111001000000100 7
#142000000
b00010000101101011110011101110011 !
b00000001011010100000101011010111 "
b00000000001000000000001001010011 #
b01 )
b00010000101101011110011101110011 ,
b00000001011010100000101011010111 -
b01 /
b00000000001000000000001001010011 0
b000000000001000000000001001010011 7
#144000000
b00101100010011011000010110010011 !
b00000010010000111100010011111111 "
b00101110010011111100010111111111 #
b10 )
b00101100010011011000010110010011 ,
b00000010010000111100010011111111 -
b10 /
b00101110010011111100010111111111 0
b000101110010011111100010111111111 7
#146000000
b00110010100010000011110101010101 !
b00000110101101001110010010100101 "
b00110110101111001111110111110101 #
b00110010100010000011110101010101 ,
b00000110101101001110010010100101 -
b00110110101111001111110111110101 0
b000110110101111001111110111110101 7
#148000000
b00101011010011101010010001110111 !
b00101001101001111000011101100001 "
b01010100111101100010101111011001 #
b00 )
b00101011010011101010010001110111 ,
b00101001101001111000011101100001 -
b00 /
b01010100111101100010101111011001 0
b001010100111101100010101111011001 7
#150000000
b00000011100101111001111010001010 !
b00001000000101001110011100011110 "
b00001011101011001000010110101001 #
b00000011100101111001111010001010 ,
b00001000000101001110011100011110 -
b00001011101011001000010110101001 0
b000001011101011001000010110101001 7
#152000000
b00010000101011001100001110100111 !
b00011110000100100100110010111010 "
b00011110101111101100111110111111 #
0$
b10 )
b00010000101011001100001110100111 ,
b00011110000100100100110010111010 -
0.
b10 /
b00011110101111101100111110111111 0
b000011110101111101100111110111111 7
#154000000
b00111001100110000010000110111011 !
b00100010110001110101111100101010 "
b00011011010111110111111010010001 #
b11 )
b00111001100110000010000110111011 ,
b00100010110001110101111100101010 -
b11 /
b00011011010111110111111010010001 0
b000011011010111110111111010010001 7
#156000000
b00111011000000110000111101010110 !
b00001000101101010001111001011011 "
b00001000000000010000111001010010 #
b01 )
b00111011000000110000111101010110 ,
b00001000101101010001111001011011 -
b01 /
b00001000000000010000111001010010 0
b000001000000000010000111001010010 7
#158000000
b00101111111000001001011110001000 !
b00000110101100111101010101001111 "
b00000110101000001001010100001000 #
1$
b00101111111000001001011110001000 ,
b00000110101100111101010101001111 -
1.
b00000110101000001001010100001000 0
b000000110101000001001010100001000 7
#160000000
b00111101001111001010100011011101 !
b00100010100111000000011101000100 "
b00100000000111000000000001000100 #
b00111101001111001010100011011101 ,
b00100010100111000000011101000100 -
b00100000000111000000000001000100 0
b000100000000111000000000001000100 7
#162000000
b00101100101111110101011010110111 !
b00110001011110010101011100101000 "
b01011110001110001010110111100000 #
b00 )
b00101100101111110101011010110111 ,
b00110001011110010101011100101000 -
b00 /
b01011110001110001010110111100000 0
b001011110001110001010110111100000 7
#164000000
b00001110100110100001110010000010 !
b00011001110011100000111100011110 "
b00101000011010000010101110100000 #
0$
b00001110100110100001110010000010 ,
b00011001110011100000111100011110 -
0.
b00101000011010000010101110100000 0
b000101000011010000010101110100000 7
#166000000
b00010000011101110010010111001110 !
b00110110011011000101101101101101 "
b00100110000110110111111010100011 #
b11 )
b00010000011101110010010111001110 ,
b00110110011011000101101101101101 -
b11 /
b00100110000110110111111010100011 0
b000100110000110110111111010100011 7
#168000000
b00111101110100100011000101000110 !
b00101010101000001101100011111111 "
b00010111011100101110100110111001 #
1$
b00111101110100100011000101000110 ,
b00101010101000001101100011111111 -
1.
b00010111011100101110100110111001 0
b000010111011100101110100110111001 7
#170000000
b00100011101000011110010111011100 !
b00111000100101011101111011110100 "
b00111011101101011111111111111100 #
b10 )
b00100011101000011110010111011100 ,
b00111000100101011101111011110100 -
b10 /
b00111011101101011111111111111100 0
b000111011101101011111111111111100 7
#172000000
b00111011111001100101001011010111 !
b00110010101000101101011011101101 "
b00001001010001001000010000111010 #
0$
b11 )
b00111011111001100101001011010111 ,
b00110010101000101101011011101101 -
0.
b11 /
b00001001010001001000010000111010 0
b000001001010001001000010000111010 7
#174000000
b00100000110101000111001000101011 !
b00000001110001001111011111110110 "
b00100001000100001000010111011101 #
1$
b00100000110101000111001000101011 ,
b00000001110001001111011111110110 -
1.
b00100001000100001000010111011101 0
b000100001000100001000010111011101 7
#176000000
b00000101001100110111011101111111 !
b00000110111011111110010110100111 "
b00000111111111111111011111111111 #
0$
b10 )
b00000101001100110111011101111111 ,
b00000110111011111110010110100111 -
0.
b10 /
b00000111111111111111011111111111 0
b000000111111111111111011111111111 7
#178000000
b00010000100011110110000011011100 !
b00111001011000100101011000001101 "
b00111001111011110111011011011101 #
b00010000100011110110000011011100 ,
b00111001011000100101011000001101 -
b00111001111011110111011011011101 0
b000111001111011110111011011011101 7
#180000000
b00100101111100111100110000110010 !
b00100000101100000011000100010111 "
b00000101010000111111110100100101 #
1$
b11 )
b00100101111100111100110000110010 ,
b00100000101100000011000100010111 -
1.
b11 /
b00000101010000111111110100100101 0
b000000101010000111111110100100101 7
#182000000
b00101111110101000101001000011110 !
b00000011010100011110100000100010 "
b00000011010100000100000000000010 #
0$
b01 )
b00101111110101000101001000011110 ,
b00000011010100011110100000100010 -
0.
b01 /
b00000011010100000100000000000010 0
b000000011010100000100000000000010 7
#184000000
b00010111000110011101110011000010 !
b00111101111101000000100001100111 "
b00010101000100000000100001000010 #
1$
b00010111000110011101110011000010 ,
b00111101111101000000100001100111 -
1.
b00010101000100000000100001000010 0
b000010101000100000000100001000010 7
#186000000
b00110011000010000010101010001101 !
b00001001001001100001001111010011 "
b00111100001011100011111001100001 #
b00 )
b00110011000010000010101010001101 ,
b00001001001001100001001111010011 -
b00 /
b00111100001011100011111001100001 0
b000111100001011100011111001100001 7
#188000000
b00001001110010111001111110100100 !
b00011100011010000111100000100111 "
b00001000010010000001100000100100 #
0$
b01 )
b00001001110010111001111110100100 ,
b00011100011010000111100000100111 -
0.
b01 /
b00001000010010000001100000100100 0
b000001000010010000001100000100100 7
#190000000
b00010110110001010100010010000110 !
b00000111010010001110100100001000 "
b00010111110011011110110110001110 #
b10 )
b00010110110001010100010010000110 ,
b00000111010010001110100100001000 -
b10 /
b00010111110011011110110110001110 0
b000010111110011011110110110001110 7
#192000000
b00001011010110010000111100111111 !
b00001001001110100010111011100001 "
b00000010011000110010000111011110 #
1$
b11 )
b00001011010110010000111100111111 ,
b00001001001110100010111011100001 -
1.
b11 /
b00000010011000110010000111011110 0
b000000010011000110010000111011110 7
#194000000
b00011100010010011000111100110100 !
b00001100111010011010100000001101 "
b00001100010010011000100000000100 #
0$
b01 )
b00011100010010011000111100110100 ,
b00001100111010011010100000001101 -
0.
b01 /
b00001100010010011000100000000100 0
b000001100010010011000100000000100 7
#196000000
b00001100010001011010111011101001 !
b00001011111110110000010001010001 "
b00001111111111111010111011111001 #
1$
b10 )
b00001100010001011010111011101001 ,
b00001011111110110000010001010001 -
1.
b10 /
b00001111111111111010111011111001 0
b000001111111111111010111011111001 7
#198000000
b00010010101011000111111010110000 !
b00011100011001110111001111111001 "
b00001110110010110000110101001001 #
b11 )
b00010010101011000111111010110000 ,
b00011100011001110111001111111001 -
b11 /
b00001110110010110000110101001001 0
b000001110110010110000110101001001 7
#200000000
b00110010010001001101101100111011 !
b00101111011000000011101010111100 "
b00111111011001001111101110111111 #
0$
b10 )
b00110010010001001101101100111011 ,
b00101111011000000011101010111100 -
0.
b10 /
b00111111011001001111101110111111 0
b000111111011001001111101110111111 7
